pyActuator/__init__.py
pyActuator/_pyActuator.cp38-win_amd64.pyd
pyActuator/py.typed
pyactuator-0.0.5.dist-info/METADATA
pyactuator-0.0.5.dist-info/WHEEL
pyactuator-0.0.5.dist-info/licenses/LICENSE
pyactuator-0.0.5.dist-info/RECORD
