Metadata-Version: 2.1
Name: pyActuator
Version: 0.0.5
Summary: pyActuator ported from C++
Author-Email: Jake Taranov <jtaranov@irisdynamics.com>
Requires-Python: >=3.8
